BaseWriter.py
CsvWriter.py
XlsWriter.py
robotframework_tabular_report-0.2.0.dist-info/METADATA
robotframework_tabular_report-0.2.0.dist-info/WHEEL
robotframework_tabular_report-0.2.0.dist-info/top_level.txt
robotframework_tabular_report-0.2.0.dist-info/RECORD
