Metadata-Version: 2.4
Name: robotframework-tabular-report
Version: 0.2.0
Summary: Robot Framework prerebotmodifiers for tabular test results
Requires-Python: >=3.10
Requires-Dist: robotframework
Requires-Dist: xlsxwriter
